kagiso_smart_404/__init__.py
kagiso_smart_404/constants.py
kagiso_smart_404/middleware.py
kagiso_smart_404/utils.py
kagiso_smart_404/views.py
kagiso_smart_404/migrations/0001_trigram_index.py
kagiso_smart_404/migrations/__init__.py
kagiso_smart_404/tests/__init__.py
kagiso_smart_404/tests/test_utils.py
kagiso_smart_404/tests/urls.py
kagiso_smart_404/tests/settings/__init__.py
kagiso_smart_404/tests/settings/ci.py
kagiso_smart_404/tests/settings/test.py
kagiso_smart_404-3.0.0.dist-info/DESCRIPTION.rst
kagiso_smart_404-3.0.0.dist-info/METADATA
kagiso_smart_404-3.0.0.dist-info/RECORD
kagiso_smart_404-3.0.0.dist-info/WHEEL
kagiso_smart_404-3.0.0.dist-info/metadata.json
kagiso_smart_404-3.0.0.dist-info/top_level.txt
