Metadata-Version: 2.0
Name: kagiso-smart-404
Version: 3.0.0
Summary: Kagiso Smart 404
Home-page: https://github.com/Kagiso-Future-Media/kagiso_smart_404
Author: Kagiso Media
Author-email: development@kagiso.io
License: UNKNOWN
Platform: UNKNOWN
Requires-Dist: wagtail (>=1.8.0)
